padlock_env/__init__.py
padlock_env/env.py
padlock_env-0.1.0.dist-info/LICENSE
padlock_env-0.1.0.dist-info/METADATA
padlock_env-0.1.0.dist-info/WHEEL
padlock_env-0.1.0.dist-info/entry_points.txt
padlock_env-0.1.0.dist-info/top_level.txt
padlock_env-0.1.0.dist-info/RECORD
