Metadata-Version: 2.1
Name: padlock-env
Version: 0.1.0
Summary: Awesome padlock_env created by cyprienc
Home-page: https://github.com/cyprienc/padlock-env/
Author: cyprienc
License-File: LICENSE
Requires-Dist: gymnasium (==0.26.3)
Requires-Dist: numpy (>=1.19.3)
Provides-Extra: test
Requires-Dist: pytest ; extra == 'test'
Requires-Dist: coverage ; extra == 'test'
Requires-Dist: flake8 ; extra == 'test'
Requires-Dist: black ; extra == 'test'
Requires-Dist: isort ; extra == 'test'
Requires-Dist: pytest-cov ; extra == 'test'
Requires-Dist: codecov ; extra == 'test'
Requires-Dist: mypy ; extra == 'test'
Requires-Dist: gitchangelog ; extra == 'test'
Requires-Dist: mkdocs ; extra == 'test'
